grad_tts/__init__.py
grad_tts/utils.py
grad_tts/model/__init__.py
grad_tts/model/base.py
grad_tts/model/diffusion.py
grad_tts/model/params.py
grad_tts/model/text_encoder.py
grad_tts/model/tts.py
grad_tts/model/utils.py
grad_tts/model/hifi_gan/__init__.py
grad_tts/model/hifi_gan/env.py
grad_tts/model/hifi_gan/hifigan-config.json
grad_tts/model/hifi_gan/meldataset.py
grad_tts/model/hifi_gan/models.py
grad_tts/model/hifi_gan/xutils.py
grad_tts/model/monotonic_align/__init__.py
grad_tts/model/monotonic_align/core.cp38-win_amd64.pyd
grad_tts/model/monotonic_align/core.pyx
grad_tts/model/monotonic_align/setup.py
grad_tts/text/__init__.py
grad_tts/text/cleaners.py
grad_tts/text/cmu_dictionary
grad_tts/text/cmudict.py
grad_tts/text/numbers.py
grad_tts/text/symbols.py
grad_tts-0.0.4.dist-info/LICENSE
grad_tts-0.0.4.dist-info/METADATA
grad_tts-0.0.4.dist-info/WHEEL
grad_tts-0.0.4.dist-info/top_level.txt
grad_tts-0.0.4.dist-info/RECORD
